{
  "writer": "빛나는별밤",
  "title": "저당 현미밥과 채소 볶음",
  "summary": "건강한 저당 식사, 현미밥과 다양한 채소를 볶아 만든 영양 만점 레시피",
  "portion": "2인분",
  "time": "30분",
  "level": "중급",
  "ingredient": {
    "현미": "1컵",
    "브로콜리": "100g",
    "당근": "1개",
    "피망": "1개",
    "양파": "1개",
    "올리브유": "2큰술"
  },
  "sauce": {
    "저염 간장": "2큰술",
    "에리스리톨": "1작은술",
    "마늘 (다진 것)": "1작은술"
  },
  "knowHow": [
    "현미는 미리 물에 불려 두면 더 부드럽게 조리됩니다.",
    "채소는 취향에 맞게 변경 가능합니다."
  ],
  "step_list": [
    "1단계: 현미를 씻고 물에 30분 정도 불린 후, 밥솥에 넣고 일반 쌀밥처럼 밥을 짓습니다.",
    "2단계: 팬에 올리브유를 두르고 다진 마늘을 볶은 후, 준비한 채소들을 넣고 볶습니다.",
    "3단계: 채소가 익으면 저염 간장과 에리스리톨을 넣고 잘 섞어 볶습니다.",
    "4단계: 밥이 완성되면 접시에 담고 볶은 채소를 올려서 서빙합니다."
  ],
  "tip": "채소는 계절에 따라 다양하게 변경 가능합니다.",
  "category_time": "저녁",
  "category_menu": "기타"
}