{
  "writer": "또먹찌",
  "title": "[당뇨식단] 칼로리는 낮추고 포만감은 더한 초간단 참치샌드위치",
  "summary": "마요네즈 대신 그릭요거트를 넣어 칼로리는 낮추고 포만감은 더한 초간단 참치샌드위치 소개 해드려요. 꼭 한번 만들어보세요 :) ♥ 유튜브 [또먹찌] 다양한 당뇨레시피 가득 !! 꼭 보러오세요 ♥",
  "portion": "1인분",
  "time": "15분 이내",
  "level": "아무나",
  "ingredient": {
    "통밀식빵 2장": "구매",
    "그릭요거트 100g": "구매",
    "방울토마토 5개": "구매",
    "치즈 1장": "구매",
    "참치 85g": "구매",
    "상추 5-7장": "구매",
    "양파 30g": "구매",
    "당근 50g": "구매"
  },
  "sauce": {
    "소금 약간": "구매",
    "후추 약간": "구매",
    "알룰로스 1큰술": "구매"
  },
  "knowHow": [
    "https://www.10000recipe.com/recipe/6897891",
    "https://www.10000recipe.com/recipe/6858178",
    "https://www.10000recipe.com/recipe/6894087",
    "https://www.10000recipe.com/recipe/6872965",
    "https://www.10000recipe.com/recipe/6895816",
    "https://www.10000recipe.com/recipe/6897186",
    "https://www.10000recipe.com/recipe/6894989",
    "https://www.10000recipe.com/recipe/6895308",
    "https://www.10000recipe.com/recipe/6871766",
    "https://www.10000recipe.com/recipe/6893627",
    "https://www.10000recipe.com/recipe/6887227",
    "https://www.10000recipe.com/recipe/6899727",
    "https://www.10000recipe.com/recipe/6895367"
  ],
  "step_list": [
    {
      "당근 얇게 채 썰어주고 양파 잘게 다져주고 토마토 반 잘라주세요.": 0
    },
    {
      "그릭요거트에 기름 뺀 참치 넣고 양파, 양념재료 넣어 잘 섞어주세요.": 0
    },
    {
      "당근에 소금, 후추 약간 넣고 중약불에 살짝만 볶아 익혀주세요.": 0
    },
    {
      "통밀식빵에 재료 차곡 차곡 얹고 랩으로 꽁꽁 감싼 뒤 먹기 좋게 반 잘라주면 초간단 참치샌드위치 완성 !!": 0
    }
  ],
  "tip": "",
  "category_time": "아침",
  "category_menu": "기타",
  "_classification_note": "The recipe is for a simple tuna sandwich, which is typically considered a breakfast item. It does not fit into other specific categories like 구이 or 국물."
}