{
  "writer": "해질녘고양이",
  "title": "저당 간장 양념 오이 절임",
  "summary": "건강한 재료로 만든 저당 간장 양념 오이 절임",
  "portion": "4인분",
  "time": "20분",
  "level": "쉬움",
  "ingredient": {
    "오이": "4개",
    "소금": "1큰술",
    "현미식초": "4큰술",
    "물": "1컵"
  },
  "sauce": {
    "스테비아": "1큰술",
    "간장": "3큰술",
    "참기름": "1큰술",
    "다진 마늘": "1작은술"
  },
  "knowHow": [
    "오이는 소금을 뿌려 10분간 두어 수분을 제거합니다.",
    "양념은 잘 섞어둡니다."
  ],
  "step_list": [
    "오이를 얇게 썰고, 소금을 뿌려 10분간 둡니다.",
    "오이에서 나온 수분을 제거한 후, 현미식초와 물을 섞어 절임 국물을 만듭니다.",
    "만든 절임 국물에 오이를 넣고, 스테비아와 간장, 참기름, 다진 마늘을 섞어 양념합니다.",
    "잘 섞인 오이를 10분 정도 재워서 맛을 배게 한 후, 냉장고에 보관합니다."
  ],
  "tip": "얼린 후 해동하면 더욱 아삭한 식감을 즐길 수 있습니다.",
  "category_time": "간식",
  "category_menu": "절임"
}