{
  "writer": "코끼리의눈썹",
  "title": "저당 야채 스프",
  "summary": "건강한 재료로 만든 저당 야채 스프",
  "portion": "4인분",
  "time": "30분",
  "level": "중급",
  "ingredient": {
    "현미밥": "2컵",
    "당근": "1개",
    "브로콜리": "200g",
    "양파": "1개",
    "마늘": "2쪽",
    "올리브유": "2큰술"
  },
  "sauce": {
    "스테비아": "1 teaspoon",
    "소금": "1/2 teaspoon",
    "후추": "약간"
  },
  "knowHow": [
    "신선한 야채를 사용하여 더욱 맛있게 만들어보세요.",
    "기호에 따라 다른 야채를 추가할 수 있습니다."
  ],
  "step_list": [
    "양파와 마늘을 다진 후 올리브유에 볶습니다.",
    "당근과 브로콜리를 추가하여 함께 볶다가 물을 넣고 끓입니다.",
    "스테비아, 소금, 후추로 간을 맞춘 후 현미밥을 넣고 한소끔 끓입니다."
  ],
  "tip": "스프를 더 걸쭉하게 만들고 싶다면 믹서에 갈아주세요.",
  "category_time": "간식",
  "category_menu": "국물"
}