{
  "writer": "초코송이전사",
  "title": "저당 귀리 죽",
  "summary": "건강한 귀리로 만든 저당 죽, 아침식사로 제격입니다.",
  "portion": "2인분",
  "time": "30분",
  "level": "중급",
  "ingredient": {
    "귀리": "1컵",
    "물": "4컵",
    "소금": "1/2작은술",
    "아몬드 우유": "1컵",
    "바나나": "1개",
    "아몬드 슬라이스": "2큰술"
  },
  "sauce": {
    "스테비아": "1작은술",
    "계피가루": "1/2작은술"
  },
  "knowHow": [
    "귀리를 밤새 물에 담가두면 부드럽고 빠르게 조리됩니다.",
    "죽이 너무 걸쭉하면 물을 추가해 조절하세요."
  ],
  "step_list": [
    "귀리를 깨끗이 씻어 불린 후 물과 함께 냄비에 넣습니다.",
    "중불에서 20분간 끓이며 저어주고, 필요에 따라 물을 추가합니다.",
    "죽이 걸쭉해지면 소금과 아몬드 우유를 넣고 5분 더 끓입니다.",
    "완성된 죽을 그릇에 담고, 슬라이스한 바나나와 아몬드를 올립니다.",
    "스테비아와 계피가루를 뿌려 맛을 더합니다."
  ],
  "tip": "다양한 과일이나 견과류로 토핑하여 변화를 줄 수 있습니다.",
  "category_time": "아침",
  "category_menu": "죽"
}