{
  "writer": "젤리주먹펀치",
  "title": "저당 귀리 팬케이크",
  "summary": "스테비아로 단맛을 더한 건강한 귀리 팬케이크입니다.",
  "portion": "2인분",
  "time": "20분",
  "level": "쉬움",
  "ingredient": {
    "귀리 가루": "1컵",
    "우유": "1컵",
    "계란": "1개",
    "바나나": "1개",
    "베이킹 파우더": "1작은술"
  },
  "sauce": {
    "스테비아": "2작은술",
    "올리브 오일": "2큰술"
  },
  "knowHow": [
    "팬이 뜨겁게 달궈진 후에 반죽을 부으세요.",
    "팬케이크를 뒤집을 때는 가장자리가 살짝 마르기 시작할 때가 적당합니다."
  ],
  "step_list": [
    "모든 재료를 큰 볼에 넣고 잘 섞어줍니다.",
    "달군 팬에 올리브 오일을 두르고, 반죽을 한 스푼씩 떠서 구워줍니다.",
    "양면이 노릇노릇하게 구워지면 접시에 담아줍니다."
  ],
  "tip": "구운 팬케이크 위에 요거트나 과일을 올려서 색다른 맛을 즐겨보세요.",
  "category_time": "아침",
  "category_menu": "디저트"
}