{
  "writer": "하늘빛꿈결",
  "title": "저당 퀴노아 샐러드",
  "summary": "영양 가득한 저당 퀴노아 샐러드로 건강한 저녁을 즐겨보세요.",
  "portion": "4인분",
  "time": "30분",
  "level": "중",
  "ingredient": {
    "퀴노아": "1컵",
    "오이": "1개",
    "방울토마토": "10개",
    "파프리카": "1개",
    "아보카도": "1개",
    "올리브유": "3큰술"
  },
  "sauce": {
    "레몬즙": "2큰술",
    "스테비아": "1큰술",
    "소금": "약간",
    "후추": "약간"
  },
  "knowHow": [
    "퀴노아는 물에 잘 씻어 조리하세요.",
    "야채는 신선한 것을 사용하세요."
  ],
  "step_list": [
    "1단계: 퀴노아를 물에 씻고, 끓는 물에 15분 정도 삶습니다.",
    "2단계: 삶은 퀴노아를 식힌 후, 잘게 썬 오이, 방울토마토, 파프리카, 아보카도를 넣습니다.",
    "3단계: 올리브유, 레몬즙, 스테비아, 소금, 후추를 섞어 드레싱을 만들어 샐러드에 뿌립니다.",
    "4단계: 모든 재료를 잘 섞어 접시에 담아 완성합니다."
  ],
  "tip": "더욱 풍부한 맛을 원하면 허브를 추가해보세요.",
  "category_time": "저녁",
  "category_menu": "샐러드"
}