{
  "writer": "달빛소나기",
  "title": "저당 김치 볶음밥",
  "summary": "건강한 저당 재료로 만든 김치 볶음밥",
  "portion": "2인분",
  "time": "20분",
  "level": "중간",
  "ingredient": {
    "현미밥": "2공기",
    "잘게 썬 김치": "1컵",
    "양파": "1개",
    "당근": "1/2개",
    "대파": "1대",
    "식용유": "2큰술",
    "계란": "2개"
  },
  "sauce": {
    "간장": "1큰술",
    "스테비아": "1작은술"
  },
  "knowHow": [
    "김치는 미리 잘게 썰어 두세요.",
    "볶음밥에 계란을 추가하면 더욱 풍부한 맛을 느낄 수 있습니다."
  ],
  "step_list": [
    "팬에 식용유를 두르고 양파와 당근을 볶습니다.",
    "양파가 투명해지면 김치를 넣고 함께 볶습니다.",
    "현미밥을 넣고 간장과 스테비아를 추가하여 잘 섞어 볶습니다.",
    "마지막으로 대파와 계란을 넣고 섞어 볶은 후 서빙합니다."
  ],
  "tip": "취향에 따라 치즈를 얹어 먹으면 더욱 맛있어요.",
  "category_time": "저녁",
  "category_menu": "볶음밥"
}