{
  "writer": "햇살속의너",
  "title": "저당 단호박 퓨레 스프",
  "summary": "부드러운 단호박과 고소한 재료로 만든 저당 스프",
  "portion": "4인분",
  "time": "30분",
  "level": "중",
  "ingredient": {
    "단호박": "400g",
    "양파": "1개",
    "마늘": "3쪽",
    "올리브유": "2큰술",
    "현미밥": "1컵",
    "채소육수": "4컵"
  },
  "sauce": {
    "스테비아": "1큰술",
    "소금": "적당량",
    "후추": "적당량"
  },
  "knowHow": [
    "단호박은 껍질을 제거하고 작은 조각으로 잘라주세요.",
    "채소육수는 미리 준비해두면 좋아요."
  ],
  "step_list": [
    "양파와 마늘을 올리브유에 볶아 향을 내주세요.",
    "단호박을 넣고 함께 볶은 후, 채소육수를 부어 끓입니다.",
    "단호박이 부드러워지면 믹서기에 갈아 퓨레 형태로 만듭니다.",
    "퓨레를 다시 냄비에 넣고, 현미밥과 스테비아, 소금, 후추를 추가하여 잘 섞습니다.",
    "저온으로 잠시 끓여서 맛을 배게 한 후 그릇에 담아 서브합니다."
  ],
  "tip": "스프의 농도를 조절하고 싶으면 물이나 채소육수를 추가하세요.",
  "category_time": "점심",
  "category_menu": "기타"
}