{
  "writer": "달빛소나기",
  "title": "저당 퀴노아 샐러드",
  "summary": "건강한 퀴노아와 신선한 채소로 만든 저당 샐러드입니다.",
  "portion": "2인분",
  "time": "20분",
  "level": "쉬움",
  "ingredient": {
    "퀴노아": "1컵",
    "방울토마토": "10개",
    "오이": "1개",
    "양파": "1/4개",
    "아보카도": "1개",
    "시금치": "한 줌"
  },
  "sauce": {
    "올리브오일": "2큰술",
    "레몬즙": "1큰술",
    "스테비아": "1티스푼",
    "소금": "약간",
    "후추": "약간"
  },
  "knowHow": [
    "퀴노아는 미리 삶아 놓아야 합니다.",
    "신선한 재료를 사용하면 더욱 맛있습니다."
  ],
  "step_list": [
    "퀴노아를 삶아 찬물에 헹군 후, 볼에 담습니다.",
    "방울토마토, 오이, 양파, 아보카도를 잘게 썰어 퀴노아에 추가합니다.",
    "시금치를 넣고, 올리브오일, 레몬즙, 스테비아, 소금, 후추로 만든 드레싱을 뿌리고 잘 섞어줍니다.",
    "그릇에 담아 서빙합니다."
  ],
  "tip": "드레싱은 미리 만들어 놓으면 더욱 간편합니다.",
  "category_time": "점심",
  "category_menu": "샐러드"
}