{
  "writer": "달빛소나기",
  "title": "저당 두부 미소국",
  "summary": "저당으로 즐기는 건강한 두부 미소국 레시피",
  "portion": "4인분",
  "time": "30분",
  "level": "쉬움",
  "ingredient": {
    "두부": "300g",
    "미역": "10g",
    "대파": "1대",
    "버섯": "100g",
    "채소육수": "800ml"
  },
  "sauce": {
    "미소된장": "3큰술",
    "스테비아": "1작은술"
  },
  "knowHow": [
    "미역은 미리 불려서 준비하세요.",
    "두부는 부드러운 것을 선택하세요."
  ],
  "step_list": [
    "1. 대파와 버섯을 잘게 썰어 준비합니다.",
    "2. 냄비에 채소육수를 붓고 대파, 버섯, 불린 미역을 넣고 끓입니다.",
    "3. 끓어오르면 두부를 넣고 미소된장을 풀어 잘 섞습니다.",
    "4. 마지막으로 스테비아를 넣고 간을 맞춘 후 5분 더 끓입니다."
  ],
  "tip": "국물이 진한 맛을 원한다면 미소된장을 살짝 더 넣어보세요.",
  "category_time": "저녁",
  "category_menu": "국물"
}