{
  "writer": "별빛바람결",
  "title": "저당 현미밥 비빔밥",
  "summary": "건강한 저당 비빔밥으로, 현미밥과 신선한 야채를 활용한 맛있는 한 끼!",
  "portion": "2인분",
  "time": "30분",
  "level": "중간",
  "ingredient": {
    "현미밥": "2공기",
    "시금치": "1컵",
    "당근": "1개",
    "오이": "1개",
    "계란": "2개",
    "닭가슴살": "150g"
  },
  "sauce": {
    "고추장": "2큰술",
    "스테비아": "1작은술",
    "참기름": "1큰술",
    "간장": "1큰술"
  },
  "knowHow": [
    "닭가슴살은 미리 삶아서 찢어두면 더욱 맛있어요.",
    "야채는 취향에 따라 다양하게 추가할 수 있어요."
  ],
  "step_list": [
    "1. 시금치를 데치고 찬물에 헹궈 물기를 제거한 후, 참기름과 소금으로 간합니다.",
    "2. 당근과 오이는 채 썰고, 계란은 부쳐서 준비합니다.",
    "3. 그릇에 현미밥을 담고 준비한 재료들을 예쁘게 올립니다.",
    "4. 준비한 고추장 소스를 뿌리고 잘 비벼서 맛있게 드세요."
  ],
  "tip": "모든 재료는 신선한 것을 사용하면 더욱 맛이 좋아요.",
  "category_time": "점심",
  "category_menu": "기타"
}