{
  "writer": "햇살속의너",
  "title": "저당 당근 케이크",
  "summary": "달콤하면서도 건강한 저당 당근 케이크입니다.",
  "portion": "8인분",
  "time": "40분",
  "level": "중급",
  "ingredient": {
    "당근": "2컵",
    "통밀가루": "1컵",
    "에리스리톨": "1/2컵",
    "계란": "3개",
    "올리브유": "1/3컵",
    "베이킹파우더": "1작은술",
    "소금": "1/2작은술",
    "계피가루": "1작은술",
    "호두": "1/2컵"
  },
  "sauce": {
    "크림치즈": "200g",
    "스테비아": "2큰술",
    "우유": "2큰술"
  },
  "knowHow": [
    "당근은 가는 채로 썰어주세요.",
    "계란과 올리브유를 잘 섞어주세요."
  ],
  "step_list": [
    "오븐을 180도로 예열합니다.",
    "큰 볼에 당근, 계란, 올리브유를 넣고 섞습니다.",
    "다른 볼에 통밀가루, 에리스리톨, 베이킹파우더, 소금, 계피가루를 혼합합니다.",
    "두 볼의 재료를 합쳐서 잘 섞습니다.",
    "호두를 넣고 가볍게 저어준 뒤, 틀에 붓고 30분간 굽습니다.",
    "크림치즈, 스테비아, 우유를 혼합하여 크림소스를 만듭니다.",
    "케이크가 식으면 소스를 뿌려서 서빙합니다."
  ],
  "tip": "케이크가 더 촉촉해지도록 당근 수분을 최대한 유지하세요.",
  "category_time": "간식",
  "category_menu": "제과제빵"
}