{
  "writer": "밥심은국력",
  "title": "설날 요리 우엉전 당뇨에 도움",
  "summary": "설날 요리 우엉전 당뇨에 도움",
  "portion": "",
  "time": "",
  "level": "아무나",
  "ingredient": {
    "우엉 200g": "구매",
    "달걀 1개": "구매",
    "튀김가루 6큰술": "구매",
    "감자전분 1큰술": "구매",
    "물 6큰술": "구매",
    "소금 약간": "구매",
    "튀김가루 3큰술": "구매",
    "부침용 식용유 적당량": "구매",
    "검은깨 고명용 약간": "구매"
  },
  "sauce": {},
  "knowHow": [
    "https://www.10000recipe.com/recipe/6876848",
    "https://www.10000recipe.com/recipe/6899727",
    "https://www.10000recipe.com/recipe/6876891",
    "https://www.10000recipe.com/recipe/6893312",
    "https://www.10000recipe.com/recipe/6898647"
  ],
  "step_list": [
    {
      "우엉전을 만들 때는 조금 굵기가 굵은 우엉이 좋아요. 양은 늘릴 때는 전체적으로 비율을 늘리세요.": "https://recipe1.ezmember.co.kr/cache/recipe/2025/01/20/978029938d27898d1a37817ee6c349751.jpg"
    },
    {
      "감자칼로 우엉 껍질을 벗기고 적당한 길이로 얇게 저며 썰어 줍니다. 식촛물을 2큰술 넣은 찬물에 10분간 담궈서 변색을 막고, 물기를 제거해요.감자칼 , 도마 , 조리용나이프 , 믹싱볼 , 채반": "https://recipe1.ezmember.co.kr/cache/recipe/2025/01/20/abd873efe247ba15acefd3a2369d10071.jpg"
    },
    {
      "전에는 보통 부침가루를 쓰는데요. 튀김가루를 써보세요. 더 바삭하고 맛있어요. 튀김가루와 찬 생수는 1:1입니다. 튀김가루 6큰술, 냉장고에 있던 생수를 6큰술, 감자전분가루 1큰술, 고운 소금 톡톡 2번을 넣어 저어줍니다. 농도가 되직하면 안 좋고, 약간 묽은 듯한 게 좋아요.믹싱볼 , 숟가락": "https://recipe1.ezmember.co.kr/cache/recipe/2025/01/20/afbe43dda9f0d7266b833f7475282fc41.jpg"
    },
    {
      "고명용 검은깨입니다.": "https://recipe1.ezmember.co.kr/cache/recipe/2025/01/20/c6e40da2d4346c75edac2198a6b197dc1.jpg"
    },
    {
      "비닐 봉지에 날 튀김가루를 넣고 편 썬 우엉을 넣어 섞어요. 지퍼백도 좋은데, 비싸니까 비닐봉지 를 사용하세요.비닐봉지": "https://recipe1.ezmember.co.kr/cache/recipe/2025/01/20/4d8222146271a866d2a0b3cf443295a21.jpg"
    },
    {
      "튀김가루가 얇게 묻어야 좋아요.": "https://recipe1.ezmember.co.kr/cache/recipe/2025/01/20/e9239ca1f28d58f0ffa7e56da9f987101.jpg"
    },
    {
      "반죽옷에 우엉을 입혀요.": "https://recipe1.ezmember.co.kr/cache/recipe/2025/01/20/fe8602f8dd984d3632d070fbf37453841.jpg"
    },
    {
      "주물 팬을 사용하면 두꺼워서 은근하게 잘 익지요. 달군 팬에 기름을 넉넉히 두르고 우엉을 두 개씩 붙여주고 검은깨를 가운데 올려요.프라이팬": "https://recipe1.ezmember.co.kr/cache/recipe/2025/01/20/918af42e896c886cf78ccd7a78182a1d1.jpg"
    },
    {
      "노릇하면 뒤집어줍니다. 기름은 보충하면서 만들어요.뒤집개": "https://recipe1.ezmember.co.kr/cache/recipe/2025/01/20/8db79b94d309281ec7f688e542df23e41.jpg"
    },
    {
      "우엉이 얇아야 잘 익어요. 두꺼우면 잘 안 익어요.": "https://recipe1.ezmember.co.kr/cache/recipe/2025/01/20/efc150cd0c12664d8c03c7238396fe881.jpg"
    },
    {
      "기름을 빼주세요.채반": "https://recipe1.ezmember.co.kr/cache/recipe/2025/01/20/6f3718988cab0cd15795da9474a0dcc21.jpg"
    },
    {
      "설날 우엉전 완성입니다.접시": "https://recipe1.ezmember.co.kr/cache/recipe/2025/01/20/e49b0275ed1a305b59a1adabf78333ae1.jpg"
    },
    {
      "양념 간장은 간장 1: 식초 1:설탕 1 비율로 만드세요.": "https://recipe1.ezmember.co.kr/cache/recipe/2025/01/20/3b6f6659f17b10d4ad8231cc103918ad1.jpg"
    },
    {
      "바삭한 우엉전 한번 만들어보세요. 즐거운 설 명절 되세요.": "https://recipe1.ezmember.co.kr/cache/recipe/2025/01/20/2cd702b91677dd50f0d07247cee2ad001.jpg"
    }
  ],
  "tip": "",
  "category_time": "저녁",
  "category_menu": "구이",
  "_classification_note": "우엉전은 주로 저녁 식사로 제공되는 전통적인 한국 요리이며, 구이 방식으로 조리됩니다."
}