{
  "writer": "해질녘고양이",
  "title": "저당 미역국",
  "summary": "담백하고 건강한 저당 미역국 레시피입니다.",
  "portion": "4인분",
  "time": "30분",
  "level": "중",
  "ingredient": {
    "미역": "50g",
    "소고기": "150g",
    "양파": "1개",
    "대파": "1대",
    "마늘": "3쪽",
    "들기름": "1큰술",
    "현미밥": "4공기",
    "물": "6컵"
  },
  "sauce": {
    "저염간장": "2큰술",
    "스테비아": "1작은술"
  },
  "knowHow": [
    "미역은 미리 불려서 준비합니다.",
    "소고기는 볶아서 더욱 깊은 맛을 냅니다."
  ],
  "step_list": [
    "1. 불린 미역을 찬물에 헹궈 물기를 제거합니다.",
    "2. 소고기는 가늘게 썰고, 양파와 대파는 채 썰어 준비합니다.",
    "3. 냄비에 들기름을 두르고 소고기를 볶다가 양파와 마늘을 넣고 볶습니다.",
    "4. 물을 넣고 끓인 후 미역을 넣고 간장을 추가하여 15분간 끓입니다.",
    "5. 대파를 넣고 간을 보고 마무리합니다."
  ],
  "tip": "국물이 걸쭉해질 때까지 끓이면 더욱 맛있습니다.",
  "category_time": "점심",
  "category_menu": "국물"
}