{
  "writer": "여우비속으로",
  "title": "저당 초코 브라우니",
  "summary": "부드럽고 진한 맛의 저당 초코 브라우니입니다.",
  "portion": "8인분",
  "time": "30분",
  "level": "중",
  "ingredient": {
    "통밀가루": "100g",
    "코코아가루": "30g",
    "스테비아": "50g",
    "버터": "100g",
    "계란": "2개",
    "우유": "100ml",
    "호두": "50g"
  },
  "sauce": {},
  "knowHow": [
    "버터는 실온에서 부드럽게 해주세요.",
    "호두는 잘게 다져주세요."
  ],
  "step_list": [
    "1. 오븐을 180도로 예열합니다.",
    "2. 볼에 부드러운 버터와 스테비아를 넣고 잘 섞습니다.",
    "3. 계란을 하나씩 넣어가며 섞고, 우유를 추가합니다.",
    "4. 통밀가루와 코코아가루를 체 쳐서 넣고 섞습니다.",
    "5. 잘게 다진 호두를 넣고 섞은 후, 반죽을 오븐용 팬에 부어줍니다.",
    "6. 25-30분간 구워준 후, 식혀서 잘라줍니다."
  ],
  "tip": "브라우니가 너무 딱딱해지지 않도록 구운 후 충분히 식혀주세요.",
  "category_time": "간식",
  "category_menu": "제과제빵"
}