{
  "writer": "초코눈물드립",
  "title": "저당 미역국",
  "summary": "건강하게 즐길 수 있는 저당 미역국 레시피입니다.",
  "portion": "4인분",
  "time": "30분",
  "level": "초급",
  "ingredient": {
    "미역": "30g",
    "소고기": "150g",
    "두부": "200g",
    "멸치": "20g",
    "양파": "1개",
    "대파": "1대",
    "참기름": "1큰술",
    "현미밥": "4공기"
  },
  "sauce": {
    "국간장": "2큰술",
    "스테비아": "1작은술",
    "다진 마늘": "1작은술"
  },
  "knowHow": [
    "미역은 물에 불려서 깨끗이 씻습니다.",
    "소고기는 미리 양념을 해두면 더 맛있습니다."
  ],
  "step_list": [
    "미역을 물에 불린 후, 소고기와 함께 참기름에 볶습니다.",
    "멸치를 넣고 물을 부어 끓인 후, 양파와 대파를 넣고 끓입니다.",
    "마지막으로 두부와 미역을 넣고 간을 맞춘 후 5분 정도 끓입니다."
  ],
  "tip": "국간장 대신 저염 간장을 사용하면 더 건강하게 즐길 수 있습니다.",
  "category_time": "아침",
  "category_menu": "국물"
}