{
  "writer": "여우비속으로",
  "title": "저당 현미밥 비빔밥",
  "summary": "건강한 저당 비빔밥으로 영양을 듬뿍 담아보세요!",
  "portion": "2인분",
  "time": "30분",
  "level": "중간",
  "ingredient": {
    "현미밥": "2공기",
    "시금치": "100g",
    "당근": "1개",
    "오이": "1개",
    "계란": "2개",
    "닭가슴살": "200g"
  },
  "sauce": {
    "간장": "2큰술",
    "스테비아": "1큰술",
    "참기름": "1큰술",
    "고춧가루": "1큰술"
  },
  "knowHow": [
    "시금치는 데쳐서 찬물에 헹군 후 물기를 제거합니다.",
    "닭가슴살은 삶아서 찢어 준비합니다."
  ],
  "step_list": [
    "1단계: 당근과 오이는 채 썰고, 준비된 재료를 모두 볼에 담습니다.",
    "2단계: 간장, 스테비아, 참기름, 고춧가루를 섞어 양념장을 만듭니다.",
    "3단계: 현미밥 위에 준비한 재료를 올리고 양념장을 뿌린 후 잘 비벼서 제공합니다."
  ],
  "tip": "신선한 야채를 사용하면 더욱 맛있습니다!",
  "category_time": "점심",
  "category_menu": "기타"
}